configTemplate/__init__.py
configTemplate/error_managers.py
configTemplate/errors.py
configTemplate/exceptions.py
configTemplate/files.py
configTemplate/templates.py
configTemplate/files/__init__.py
configTemplate/files/extras.py
configTemplate/files/files.py
configTemplate/templates/__init__.py
configTemplate/templates/base.py
configTemplate/templates/templates.py
configTemplate-0.3.2.dist-info/METADATA
configTemplate-0.3.2.dist-info/WHEEL
configTemplate-0.3.2.dist-info/top_level.txt
configTemplate-0.3.2.dist-info/RECORD
