Metadata-Version: 2.1
Name: configTemplate
Version: 0.3.2
Summary: Easily define and check configuration file structures 📂🍒
Home-page: https://github.com/RealA10N/configTemplate
Author: RealA10N
Author-email: downtown2u@gmail.com
License: UNKNOWN
Platform: UNKNOWN
Classifier: Development Status :: 4 - Beta
Classifier: Programming Language :: Python :: 3
Classifier: Programming Language :: Python :: 3.6
Classifier: Programming Language :: Python :: 3.7
Classifier: Programming Language :: Python :: 3.8
Classifier: Programming Language :: Python :: 3.9
Classifier: Operating System :: OS Independent
Requires-Python: >=3.6
Requires-Dist: termcolor (==1.1.0)
Provides-Extra: all
Requires-Dist: pyyaml (<5.5,>=5.4) ; extra == 'all'
Requires-Dist: toml (<0.11,>=0.10.2) ; extra == 'all'
Provides-Extra: dev
Requires-Dist: pytest (<6.3,>=6.2) ; extra == 'dev'
Requires-Dist: flake8 (<3.10,>=3.9) ; extra == 'dev'
Requires-Dist: pyyaml (<5.5,>=5.4) ; extra == 'dev'
Requires-Dist: toml (<0.11,>=0.10.2) ; extra == 'dev'
Provides-Extra: toml
Requires-Dist: toml (<0.11,>=0.10.2) ; extra == 'toml'
Provides-Extra: yaml
Requires-Dist: pyyaml (<5.5,>=5.4) ; extra == 'yaml'
